setup.py
countries_field/__init__.py
countries_field/fields.py
countries_field/forms.py
countries_field/tests/__init__.py
countries_field/tests/models.py
countries_field/tests/tests.py
django_countries_field.egg-info/PKG-INFO
django_countries_field.egg-info/SOURCES.txt
django_countries_field.egg-info/dependency_links.txt
django_countries_field.egg-info/not-zip-safe
django_countries_field.egg-info/requires.txt
django_countries_field.egg-info/top_level.txt