Metadata-Version: 1.1
Name: django-countries-field
Version: 0.1.0
Summary: CountriesField in Django
Home-page: https://github.com/anatoliy-larin/django-countries-field
Author: RUTUBE
Author-email: devel@rutube.ru
License: UNKNOWN
Platform: UNKNOWN
Classifier: Framework :: Django
Classifier: Intended Audience :: Developers
Classifier: Programming Language :: Python :: 2.7
